goedels_poetry/__init__.py
goedels_poetry/cli.py
goedels_poetry/framework.py
goedels_poetry/functools.py
goedels_poetry/state.py
goedels_poetry/agents/__init__.py
goedels_poetry/agents/formal_theorem_syntax_agent.py
goedels_poetry/agents/formalizer_agent.py
goedels_poetry/agents/informal_theorem_semantics_agent.py
goedels_poetry/agents/informal_theorem_syntax_agent.py
goedels_poetry/agents/proof_checker_agent.py
goedels_poetry/agents/proof_corrector_agent.py
goedels_poetry/agents/proof_parser_agent.py
goedels_poetry/agents/proof_sketcher_agent.py
goedels_poetry/agents/prover_agent.py
goedels_poetry/agents/search_query_agent.py
goedels_poetry/agents/sketch_backtrack_agent.py
goedels_poetry/agents/sketch_checker_agent.py
goedels_poetry/agents/sketch_corrector_agent.py
goedels_poetry/agents/sketch_decomposition_agent.py
goedels_poetry/agents/sketch_parser_agent.py
goedels_poetry/agents/state.py
goedels_poetry/agents/supervisor_agent.py
goedels_poetry/agents/vector_db_agent.py
goedels_poetry/agents/util/__init__.py
goedels_poetry/agents/util/common.py
goedels_poetry/agents/util/debug.py
goedels_poetry/agents/util/kimina_server.py
goedels_poetry/config/__init__.py
goedels_poetry/config/config.py
goedels_poetry/config/kimina_server.py
goedels_poetry/config/lean_explore_server.py
goedels_poetry/config/llm.py
goedels_poetry/data/__init__.py
goedels_poetry/data/config.ini
goedels_poetry/data/prompts/decomposer-backtrack.md
goedels_poetry/data/prompts/decomposer-initial.md
goedels_poetry/data/prompts/decomposer-subsequent.md
goedels_poetry/data/prompts/goedel-formalizer-v2.md
goedels_poetry/data/prompts/goedel-prover-v2-initial.md
goedels_poetry/data/prompts/goedel-prover-v2-subsequent.md
goedels_poetry/data/prompts/goedel-semiotician-v2.md
goedels_poetry/data/prompts/search-query-backtrack.md
goedels_poetry/data/prompts/search-query-initial.md
goedels_poetry/parsers/__init__.py
goedels_poetry/parsers/ast.py
goedels_poetry/parsers/util.py
goedels_poetry/util/__init__.py
goedels_poetry-1.2.8.dist-info/METADATA
goedels_poetry-1.2.8.dist-info/WHEEL
goedels_poetry-1.2.8.dist-info/entry_points.txt
goedels_poetry-1.2.8.dist-info/licenses/LICENSE
goedels_poetry-1.2.8.dist-info/RECORD
