Metadata-Version: 2.4
Name: goedels-poetry
Version: 1.2.8
Summary: A recursive, reflective POETRY algorithm variant using Goedel-Prover-V2
Project-URL: Homepage, https://KellyJDavis.github.io/goedels-poetry/
Project-URL: Repository, https://github.com/KellyJDavis/goedels-poetry
Project-URL: Documentation, https://KellyJDavis.github.io/goedels-poetry/
Author-email: Kelly J Davis <kdavis@alum.mit.edu>
License-Expression: Apache-2.0
License-File: LICENSE
Keywords: python
Classifier: Development Status :: 4 - Beta
Classifier: Intended Audience :: Developers
Classifier: License :: OSI Approved :: Apache Software License
Classifier: Programming Language :: Python
Classifier: Programming Language :: Python :: 3
Classifier: Programming Language :: Python :: 3.10
Classifier: Programming Language :: Python :: 3.11
Classifier: Programming Language :: Python :: 3.12
Classifier: Programming Language :: Python :: 3.13
Classifier: Topic :: Software Development :: Libraries :: Python Modules
Requires-Python: <4.0,>=3.10
Requires-Dist: jinja2>=3.1.6
Requires-Dist: kimina-ast-client>=0.2.2
Requires-Dist: langchain-core>=0.3.77
Requires-Dist: langchain-openai>=0.3.34
Requires-Dist: langgraph>=0.6.8
Requires-Dist: lean-xplore>=0.4.3
Requires-Dist: rich>=14.1.0
Requires-Dist: typer>=0.19.2
Requires-Dist: typing-extensions>=4.15.0
